airflow_provider_census/__init__.py
airflow_provider_census/example_dags/__init__.py
airflow_provider_census/example_dags/example_census.py
airflow_provider_census/hooks/__init__.py
airflow_provider_census/hooks/census.py
airflow_provider_census/operators/__init__.py
airflow_provider_census/operators/census.py
airflow_provider_census/sensors/__init__.py
airflow_provider_census/sensors/census.py
airflow_provider_census-2.0.0.dist-info/licenses/LICENSE
airflow_provider_census-2.0.0.dist-info/METADATA
airflow_provider_census-2.0.0.dist-info/WHEEL
airflow_provider_census-2.0.0.dist-info/entry_points.txt
airflow_provider_census-2.0.0.dist-info/top_level.txt
airflow_provider_census-2.0.0.dist-info/RECORD
