Metadata-Version: 2.4
Name: airflow-provider-census
Version: 2.0.0
Summary: A Census provider for Apache Airflow.
Author-email: Census <dev@getcensus.com>
License-Expression: MIT
Project-URL: Bug Tracker, https://github.com/sutrolabs/airflow-provider-census/issues
Project-URL: homepage, https://www.getcensus.com/
Project-URL: repository, https://github.com/sutrolabs/airflow-provider-census
Classifier: Programming Language :: Python :: 3.9
Classifier: Programming Language :: Python :: 3.10
Classifier: Programming Language :: Python :: 3.11
Classifier: Programming Language :: Python :: 3.12
Classifier: Programming Language :: Python :: 3.13
Classifier: Operating System :: OS Independent
Requires-Python: <4.0,>=3.9
License-File: LICENSE
Requires-Dist: apache-airflow<3.13,>2.0
Requires-Dist: apache-airflow-providers-http>=1.1.1
Dynamic: license-file
